ldrag/__init__.py
ldrag/config.py
ldrag/converter.py
ldrag/gptconnector.py
ldrag/graphdbconnector.py
ldrag/ontology.py
ldrag/ontology_io.py
ldrag/retriever.py
ldrag-0.2.0.dist-info/licenses/LICENSE
ldrag-0.2.0.dist-info/METADATA
ldrag-0.2.0.dist-info/WHEEL
ldrag-0.2.0.dist-info/top_level.txt
ldrag-0.2.0.dist-info/RECORD
