Metadata-Version: 2.4
Name: ldrag
Version: 0.2.0
Summary: LD-RAG: GPT-driven ontology reasoning and retrieval
Author-email: Alexander Lohr <alexander.lohr.code@gmail.com>
Requires-Python: >=3.8
License-File: LICENSE
Requires-Dist: rdflib>=6.0.0
Requires-Dist: pyvis>=0.3.1
Requires-Dist: networkx>=2.6
Requires-Dist: matplotlib>=3.4
Requires-Dist: pandas>=1.3
Requires-Dist: numpy>=1.21
Requires-Dist: scikit-learn>=1.0
Requires-Dist: xgboost>=1.5
Requires-Dist: lightgbm>=3.3
Requires-Dist: catboost>=1.0
Requires-Dist: shap>=0.41
Requires-Dist: openai>=1.0
Requires-Dist: SPARQLWrapper>=1.8.5
Dynamic: license-file
